README.rst
setup.py
bin/twentiment_client
bin/twentiment_server
twentiment/__init__.py
twentiment/classifier.py
twentiment/extract.py
twentiment/naivebayes.py
twentiment/server.py
twentiment/text.py
twentiment.egg-info/PKG-INFO
twentiment.egg-info/SOURCES.txt
twentiment.egg-info/dependency_links.txt
twentiment.egg-info/requires.txt
twentiment.egg-info/top_level.txt
twentiment/thirdparty/__init__.py
twentiment/thirdparty/probability.py