Metadata-Version: 1.1
Name: twentiment
Version: 0.1.0
Summary: Twitter sentiment analysis tool
Home-page: https://github.com/passy/twentiment
Author: Pascal Hartig
Author-email: phartig@rdrei.net
License: Licensed under the Apache License, Version 2.0 (the 'License');
